retfidf/__init__.py
retfidf/doc_retrieval.py
retfidf-0.0.2.dist-info/LICENSE.txt
retfidf-0.0.2.dist-info/METADATA
retfidf-0.0.2.dist-info/WHEEL
retfidf-0.0.2.dist-info/top_level.txt
retfidf-0.0.2.dist-info/RECORD
